LICENSE
README.md
setup.py
kft/__init__.py
kft/cli.py
kft/kf_image_scanner.py
kft/kf_upgrade_planner.py
kft.egg-info/PKG-INFO
kft.egg-info/SOURCES.txt
kft.egg-info/dependency_links.txt
kft.egg-info/entry_points.txt
kft.egg-info/requires.txt
kft.egg-info/top_level.txt