Metadata-Version: 2.1
Name: kft
Version: 0.1.1
Summary: A collection of handy wrapper tools for operators of kubeflow environments
Home-page: https://github.com/nishant-dash/kf-tools
Author: Nishant Dash
Author-email: nishant.dash@canonical.com
License: MIT License
Platform: UNKNOWN
Requires-Python: >=3.7
License-File: LICENSE
